{
  "endpoints": [
    {
      "path": "/users",
      "method": "GET",
      "description": "Retrieve a list of users",
      "schema": {
        "name": "users",
        "columns": [
          { "name": "id", "type": "integer" },
          { "name": "name", "type": "string" },
          { "name": "email", "type": "string", "unique": true },
          { "name": "msisdn", "type": "string", "unique": true }
        ],
        "description": "Schema for users with personal information."
      }
    },
    {
      "path": "/users/{user_id}/subscriptions",
      "method": "GET",
      "description": "Get subscriptions for a specified user",
      "parameters": [
        { "name": "user_id", "in": "path", "type": "integer", "required": true }
      ],
      "schema": {
        "name": "subscriptions",
        "columns": [
          { "name": "id", "type": "integer" },
          { "name": "service", "type": "string" },
          { "name": "service_duration", "type": "integer" },
          { "name": "date_subscribed", "type": "string" },
          { "name": "description", "type": "string" },
          { "name": "end_date", "type": "string" },
          { "name": "user_id", "type": "integer", "foreign_key": true }
        ],
        "description": "Schema capturing user-specific subscriptions."
      }
    }
  ]
}